casanovo/__init__.py
casanovo/casanovo.py
casanovo/config.py
casanovo/config.yaml
casanovo/utils.py
casanovo/version.py
casanovo/data/__init__.py
casanovo/data/db_utils.py
casanovo/data/ms_io.py
casanovo/data/psm.py
casanovo/denovo/__init__.py
casanovo/denovo/dataloaders.py
casanovo/denovo/evaluate.py
casanovo/denovo/model.py
casanovo/denovo/model_runner.py
casanovo/denovo/transformers.py
casanovo-5.1.2.dist-info/licenses/LICENSE
docs/images/configure-help.svg
docs/images/db-search-help.svg
docs/images/evaluate-help.svg
docs/images/help.svg
docs/images/sequence-help.svg
docs/images/train-help.svg
tests/unit_tests/test_config.py
tests/unit_tests/test_runner.py
tests/unit_tests/test_unit.py
casanovo-5.1.2.dist-info/METADATA
casanovo-5.1.2.dist-info/WHEEL
casanovo-5.1.2.dist-info/entry_points.txt
casanovo-5.1.2.dist-info/top_level.txt
casanovo-5.1.2.dist-info/RECORD
