Metadata-Version: 2.4
Name: casanovo
Version: 5.1.2
Summary: De novo mass spectrometry peptide sequencing with a transformer model
Author-email: Melih Yilmaz <melih@cs.washington.edu>, "William E. Fondrie" <fondriew@gmail.com>, Wout Bittremieux <wout.bittremieux@uantwerpen.be>
License: Apache 2.0
Project-URL: Homepage, https://github.com/Noble-Lab/casanovo
Project-URL: Documentation, https://casanovo.readthedocs.io
Project-URL: Bug Tracker, https://github.com/Noble-Lab/casanovo/issues
Project-URL: Discussion Board, https://github.com/Noble-Lab/casanovo/discussions
Classifier: Programming Language :: Python :: 3
Classifier: License :: OSI Approved :: Apache Software License
Classifier: Operating System :: OS Independent
Classifier: Topic :: Scientific/Engineering :: Bio-Informatics
Requires-Python: >=3.8
License-File: LICENSE
Requires-Dist: appdirs
Requires-Dist: lightning>=2.4
Requires-Dist: click
Requires-Dist: depthcharge-ms<0.5.0,>=0.4.8
Requires-Dist: natsort
Requires-Dist: numpy<2.0
Requires-Dist: pandas
Requires-Dist: psutil
Requires-Dist: PyGithub
Requires-Dist: pylance==0.15.0
Requires-Dist: PyYAML
Requires-Dist: requests
Requires-Dist: rich-click>=1.6.1
Requires-Dist: scikit-learn
Requires-Dist: spectrum-utils>=0.5.0
Requires-Dist: tensorboard
Requires-Dist: torch>=2.2
Requires-Dist: tqdm
Provides-Extra: docs
Requires-Dist: sphinx>=4.5.0; extra == "docs"
Requires-Dist: myst-parser>=0.18.1; extra == "docs"
Requires-Dist: sphinx-book-theme>=0.3.3; extra == "docs"
Requires-Dist: sphinx-click>=5.2.1; extra == "docs"
Provides-Extra: dev
Requires-Dist: pre-commit>=2.7.1; extra == "dev"
Requires-Dist: black>=19.10b0; extra == "dev"
Requires-Dist: ppx; extra == "dev"
Requires-Dist: psims; extra == "dev"
Requires-Dist: pyteomics; extra == "dev"
Requires-Dist: pytest; extra == "dev"
Dynamic: license-file
